[
    {
        "doctype": "Payment Entry",
        "sales_invoice": "ACC-SINV-2026-00001",
        "payment_type": "Receive",
        "posting_date": "2026-02-10"
    },
    {
        "doctype": "Payment Entry",
        "sales_invoice": "ACC-SINV-2026-00002",
        "payment_type": "Receive",
        "posting_date": "2026-02-11"
    },
    {
        "doctype": "Payment Entry",
        "sales_invoice": "ACC-SINV-2026-00003",
        "payment_type": "Receive",
        "posting_date": "2026-02-12"
    },
    {
        "doctype": "Payment Entry",
        "sales_invoice": "ACC-SINV-2026-00004",
        "payment_type": "Receive",
        "posting_date": "2026-02-13"
    }
]